mdabojbot/__init__.py
mdabojbot/__main__.py
mdabojbot/bot.py
mdabojbot/common/__init__.py
mdabojbot/common/commands.py
mdabojbot/common/models.py
mdabojbot/db.py
mdabojbot/prediction/__init__.py
mdabojbot/prediction/commands.py
mdabojbot/prediction/models.py
mdabojbot/prediction/service.py
mdabojbot/user/__init__.py
mdabojbot/user/commands.py
mdabojbot/user/constants.py
mdabojbot/user/models.py
mdabojbot/user/service.py
mdabojbot/utils.py
mdabojbot-0.1.1.dist-info/METADATA
mdabojbot-0.1.1.dist-info/WHEEL
mdabojbot-0.1.1.dist-info/entry_points.txt
mdabojbot-0.1.1.dist-info/RECORD
