Metadata-Version: 2.4
Name: mdabojbot
Version: 0.1.1
Summary: Тот самый токсичный бот в телеграм группе.
Author: skv0zsneg
Author-email: klimentlamonov@yandex.ru
Requires-Python: >=3.12
Classifier: Programming Language :: Python :: 3
Classifier: Programming Language :: Python :: 3.12
Classifier: Programming Language :: Python :: 3.13
Classifier: Programming Language :: Python :: 3.14
Requires-Dist: aiosqlite (>=0.21.0,<0.22.0)
Requires-Dist: python-decouple (>=3.8,<4.0)
Requires-Dist: python-telegram-bot (>=22.5,<23.0)
Requires-Dist: sqlalchemy (>=2.0.43,<3.0.0)
